XStatic_CKEditor-3.6.4.0-py3.13-nspkg.pth
xstatic/pkg/ckeditor/__init__.py
xstatic/pkg/ckeditor/data/.htaccess
xstatic/pkg/ckeditor/data/LICENSE.html
xstatic/pkg/ckeditor/data/ckeditor.js
xstatic/pkg/ckeditor/data/ckeditor_basic.js
xstatic/pkg/ckeditor/data/config.js
xstatic/pkg/ckeditor/data/contents.css
xstatic/pkg/ckeditor/data/adapters/jquery.js
xstatic/pkg/ckeditor/data/images/spacer.gif
xstatic/pkg/ckeditor/data/lang/_languages.js
xstatic/pkg/ckeditor/data/lang/_translationstatus.txt
xstatic/pkg/ckeditor/data/lang/af.js
xstatic/pkg/ckeditor/data/lang/ar.js
xstatic/pkg/ckeditor/data/lang/bg.js
xstatic/pkg/ckeditor/data/lang/bn.js
xstatic/pkg/ckeditor/data/lang/bs.js
xstatic/pkg/ckeditor/data/lang/ca.js
xstatic/pkg/ckeditor/data/lang/cs.js
xstatic/pkg/ckeditor/data/lang/cy.js
xstatic/pkg/ckeditor/data/lang/da.js
xstatic/pkg/ckeditor/data/lang/de.js
xstatic/pkg/ckeditor/data/lang/el.js
xstatic/pkg/ckeditor/data/lang/en-au.js
xstatic/pkg/ckeditor/data/lang/en-ca.js
xstatic/pkg/ckeditor/data/lang/en-gb.js
xstatic/pkg/ckeditor/data/lang/en.js
xstatic/pkg/ckeditor/data/lang/eo.js
xstatic/pkg/ckeditor/data/lang/es.js
xstatic/pkg/ckeditor/data/lang/et.js
xstatic/pkg/ckeditor/data/lang/eu.js
xstatic/pkg/ckeditor/data/lang/fa.js
xstatic/pkg/ckeditor/data/lang/fi.js
xstatic/pkg/ckeditor/data/lang/fo.js
xstatic/pkg/ckeditor/data/lang/fr-ca.js
xstatic/pkg/ckeditor/data/lang/fr.js
xstatic/pkg/ckeditor/data/lang/gl.js
xstatic/pkg/ckeditor/data/lang/gu.js
xstatic/pkg/ckeditor/data/lang/he.js
xstatic/pkg/ckeditor/data/lang/hi.js
xstatic/pkg/ckeditor/data/lang/hr.js
xstatic/pkg/ckeditor/data/lang/hu.js
xstatic/pkg/ckeditor/data/lang/id.js
xstatic/pkg/ckeditor/data/lang/is.js
xstatic/pkg/ckeditor/data/lang/it.js
xstatic/pkg/ckeditor/data/lang/ja.js
xstatic/pkg/ckeditor/data/lang/ka.js
xstatic/pkg/ckeditor/data/lang/km.js
xstatic/pkg/ckeditor/data/lang/ko.js
xstatic/pkg/ckeditor/data/lang/lt.js
xstatic/pkg/ckeditor/data/lang/lv.js
xstatic/pkg/ckeditor/data/lang/mk.js
xstatic_ckeditor-3.6.4.0.dist-info/METADATA
xstatic_ckeditor-3.6.4.0.dist-info/WHEEL
xstatic_ckeditor-3.6.4.0.dist-info/namespace_packages.txt
xstatic_ckeditor-3.6.4.0.dist-info/top_level.txt
xstatic_ckeditor-3.6.4.0.dist-info/RECORD
