Metadata-Version: 2.4
Name: XStatic-CKEditor
Version: 3.6.4.0
Summary: CKEditor 3.6.4 (XStatic packaging standard)
Home-page: http://ckeditor.com/
Maintainer: Thomas Waldmann
Maintainer-email: tw@waldmann-edv.de
License: (same as CKEditor)
Keywords: ckeditor xstatic
Platform: any
Dynamic: description
Dynamic: home-page
Dynamic: keywords
Dynamic: license
Dynamic: maintainer
Dynamic: maintainer-email
Dynamic: platform
Dynamic: summary
